odoo/addons/base_user_show_email/README.rst
odoo/addons/base_user_show_email/__init__.py
odoo/addons/base_user_show_email/__manifest__.py
odoo/addons/base_user_show_email/i18n/base_user_show_email.pot
odoo/addons/base_user_show_email/i18n/it.po
odoo/addons/base_user_show_email/readme/CONTRIBUTORS.md
odoo/addons/base_user_show_email/readme/DESCRIPTION.md
odoo/addons/base_user_show_email/static/description/icon.png
odoo/addons/base_user_show_email/static/description/index.html
odoo/addons/base_user_show_email/views/login_layout.xml
odoo/addons/base_user_show_email/views/res_users_view.xml
odoo_addon_base_user_show_email-18.0.1.0.0.2.dist-info/METADATA
odoo_addon_base_user_show_email-18.0.1.0.0.2.dist-info/WHEEL
odoo_addon_base_user_show_email-18.0.1.0.0.2.dist-info/top_level.txt
odoo_addon_base_user_show_email-18.0.1.0.0.2.dist-info/RECORD
